Workbook
Name aporte: 'SIMULADOR INVESTIMENTOS'!$D$15
Name patrimonio: 'SIMULADOR INVESTIMENTOS'!$D$18
Name qdt_anos: 'SIMULADOR INVESTIMENTOS'!$D$16
Name rendimento_carteira: 'SIMULADOR INVESTIMENTOS'!$D$11
Name salario: 'SIMULADOR INVESTIMENTOS'!$D$10
Name sugestao_investimento: 'SIMULADOR INVESTIMENTOS'!$D$12
Name taxa_mensal: 'SIMULADOR INVESTIMENTOS'!$D$17

Sheet SIMULADOR INVESTIMENTOS
B9: SIMULADOR
B10: Salário | D10: 8000
B11: Rendimento Carteira | D11: 0.006
B12: Sugestão de Investimento | D12: =D10*30% -> 2400
B14: INVESTIMENTO MENSAL
B15: Quanto investir por mês? | D15: 2400
B16: Por quantos anos? | D16: 5
B17: Taxa de rendimento mensal? | D17: 0.01079
B18: Patrimônio acumulado? | D18: =FV(taxa_mensal,qdt_anos*12,aporte*-1) -> 201064.59
B19: Dividendo mensais? | D19: =patrimonio*rendimento_carteira -> 1206.3876
B21: CENÁRIOS | D21: DIVIDENDO
A22: 2 | B22: Quanto em 2 anos? | C22: =FV($D$17,$A22*12,$D$15*-1) -> 65346.306 | D22: =C22*rendimento_carteira -> 392.07783
A23: 5 | B23: Quanto em 5 anos? | C23: =FV($D$17,$A23*12,$D$15*-1) -> 201064.59 | D23: =C23*rendimento_carteira -> 1206.3876
A24: 10 | B24: Quanto em 10 anos? | C24: =FV($D$17,$A24*12,$D$15*-1) -> 583882.11 | D24: =C24*rendimento_carteira -> 3503.2927
A25: 20 | B25: Quanto em 20 anos? | C25: =FV($D$17,$A25*12,$D$15*-1) -> 2700476.2 | D25: =C25*rendimento_carteira -> 16202.857
A26: 30 | B26: Quanto em 30 anos? | C26: =FV($D$17,$A26*12,$D$15*-1) -> 10373207 | D26: =C26*rendimento_carteira -> 62239.243
B30: PERFIL | D30: Agressivo
B31: VALOR INVESTIDO POR MÊS | D31: =aporte -> 2400
B33: TIPOS DE FIIIs | C33: PERCENTUAL SUGERIDO | D33: VALOR
B34: PAPEL | C34: =VLOOKUP($D$30&"-"&B34,ELEMENTOS!$B$4:$E$22,4,FALSE) -> 0.5 | D34: =C34*$D$31 -> 1200
B35: TIJOLO | C35: =VLOOKUP($D$30&"-"&B35,ELEMENTOS!$B$4:$E$22,4,FALSE) -> 0.1 | D35: =C35*$D$31 -> 240
B36: HÍBRIDO | C36: =VLOOKUP($D$30&"-"&B36,ELEMENTOS!$B$4:$E$22,4,FALSE) -> 0.05 | D36: =C36*$D$31 -> 120
B37: FOFs | C37: =VLOOKUP($D$30&"-"&B37,ELEMENTOS!$B$4:$E$22,4,FALSE) -> 0.05 | D37: =C37*$D$31 -> 120
B38: DESENVOLVIMENTO | C38: =VLOOKUP($D$30&"-"&B38,ELEMENTOS!$B$4:$E$22,4,FALSE) -> 0.2 | D38: =C38*$D$31 -> 480
B39: HOTELARIA | C39: =VLOOKUP($D$30&"-"&B39,ELEMENTOS!$B$4:$E$22,4,FALSE) -> 0.1 | D39: =C39*$D$31 -> 240
D40: =SUM(D34:D39) -> 2400

Sheet ELEMENTOS
B4: CHAVE | C4: PERFIL | D4: TIPOS DE FIIIs | E4: %
B5: =$C$5&"-"&D5 -> Conservador-PAPEL | C5: Conservador | D5: PAPEL | E5: 0.3 | H5: Moderado-PAPEL | I5: =VLOOKUP(H5,B5:E22,4,FALSE) -> 0.32
B6: =$C$5&"-"&D6 -> Conservador-TIJOLO | C6: Conservador | D6: TIJOLO | E6: 0.5
B7: =$C$5&"-"&D7 -> Conservador-HÍBRIDO | C7: Conservador | D7: HÍBRIDO | E7: 0.1
B8: =$C$5&"-"&D8 -> Conservador-FOFs | C8: Conservador | D8: FOFs | E8: 0.1
B9: =$C$5&"-"&D9 -> Conservador-DESENVOLVIMENTO | C9: Conservador | D9: DESENVOLVIMENTO | E9: 0
B10: =$C$5&"-"&D10 -> Conservador-HOTELARIA | C10: Conservador | D10: HOTELARIA | E10: 0
B11: =$C$11&"-"&D11 -> Moderado-PAPEL | C11: Moderado | D11: PAPEL | E11: 0.32
B12: =$C$11&"-"&D12 -> Moderado-TIJOLO | C12: Moderado | D12: TIJOLO | E12: 0.35
B13: =$C$11&"-"&D13 -> Moderado-HÍBRIDO | C13: Moderado | D13: HÍBRIDO | E13: 0.08
B14: =$C$11&"-"&D14 -> Moderado-FOFs | C14: Moderado | D14: FOFs | E14: 0.05
B15: =$C$11&"-"&D15 -> Moderado-DESENVOLVIMENTO | C15: Moderado | D15: DESENVOLVIMENTO | E15: 0.1
B16: =$C$11&"-"&D16 -> Moderado-HOTELARIA | C16: Moderado | D16: HOTELARIA | E16: 0.1
B17: =$C$17&"-"&D17 -> Agressivo-PAPEL | C17: Agressivo | D17: PAPEL | E17: 0.5
B18: =$C$17&"-"&D18 -> Agressivo-TIJOLO | C18: Agressivo | D18: TIJOLO | E18: 0.1
B19: =$C$17&"-"&D19 -> Agressivo-HÍBRIDO | C19: Agressivo | D19: HÍBRIDO | E19: 0.05
B20: =$C$17&"-"&D20 -> Agressivo-FOFs | C20: Agressivo | D20: FOFs | E20: 0.05
B21: =$C$17&"-"&D21 -> Agressivo-DESENVOLVIMENTO | C21: Agressivo | D21: DESENVOLVIMENTO | E21: 0.2
B22: =$C$17&"-"&D22 -> Agressivo-HOTELARIA | C22: Agressivo | D22: HOTELARIA | E22: 0.1
